Metadata-Version: 1.1
Name: metagenomi
Version: 1.3.19
Summary: UNKNOWN
Home-page: http://metagenomi.co
Author: Metagenomi.co
Author-email: info@metagenomi.co
License: MIT
Platform: UNKNOWN
Classifier: Programming Language :: Python
Classifier: Programming Language :: Python :: 3
